ariadne_roots/__init__.py
ariadne_roots/main.py
ariadne_roots/pareto_functions.py
ariadne_roots/quantify.py
ariadne_roots-0.0.3.dist-info/LICENSE
ariadne_roots-0.0.3.dist-info/METADATA
ariadne_roots-0.0.3.dist-info/WHEEL
ariadne_roots-0.0.3.dist-info/entry_points.txt
ariadne_roots-0.0.3.dist-info/top_level.txt
ariadne_roots-0.0.3.dist-info/RECORD
