Metadata-Version: 2.1
Name: ariadne-roots
Version: 0.0.3
Summary: Ariadne root tracing GUI and trait calculator.
Author-email: Matthieu Platre <mattplatre@gmail.com>, Kian Faizi <kian@caltech.edu>, Elizabeth Berrigan <eberrigan@salk.edu>
Project-URL: Homepage, https://github.com/Salk-Harnessing-Plants-Initiative/Ariadne
Project-URL: Issues, https://github.com/Salk-Harnessing-Plants-Initiative/Ariadne/issues
Keywords: ariadne,plants,roots,phenotyping,pareto
Classifier: Programming Language :: Python :: 3
Classifier: License :: OSI Approved :: GNU General Public License v3 (GPLv3)
Classifier: Operating System :: OS Independent
Classifier: Development Status :: 4 - Beta
Requires-Python: >=3.8
License-File: LICENSE
Requires-Dist: pillow
Requires-Dist: networkx
Requires-Dist: numpy
Requires-Dist: scipy
Requires-Dist: matplotlib
Provides-Extra: dev
Requires-Dist: toml; extra == "dev"
Requires-Dist: twine; extra == "dev"
Requires-Dist: build; extra == "dev"
